devdeck_key_light/__init__.py
devdeck_key_light/key_light_toggle_control.py
devdeck_key_light/assets/key-light-off.png
devdeck_key_light/assets/key-light-on.png
tests/__init__.py
tests/testing_utils.py
tests/devdeck_key_light/__init__.py
tests/devdeck_key_light/test_keylight_toggle_control.py
devdeck_key_light-1.0.4.dist-info/METADATA
devdeck_key_light-1.0.4.dist-info/WHEEL
devdeck_key_light-1.0.4.dist-info/top_level.txt
devdeck_key_light-1.0.4.dist-info/RECORD
